webmirror/__init__.py
webmirror/webmirror.py
webmirror-1.0.0.dist-info/licenses/LICENSE
webmirror-1.0.0.dist-info/METADATA
webmirror-1.0.0.dist-info/WHEEL
webmirror-1.0.0.dist-info/entry_points.txt
webmirror-1.0.0.dist-info/top_level.txt
webmirror-1.0.0.dist-info/RECORD
